apple_reading_list_to_sqlite/__init__.py
apple_reading_list_to_sqlite/__version__.py
apple_reading_list_to_sqlite/cli.py
apple_reading_list_to_sqlite-0.2.2.dist-info/LICENSE
apple_reading_list_to_sqlite-0.2.2.dist-info/METADATA
apple_reading_list_to_sqlite-0.2.2.dist-info/WHEEL
apple_reading_list_to_sqlite-0.2.2.dist-info/entry_points.txt
apple_reading_list_to_sqlite-0.2.2.dist-info/RECORD
