Metadata-Version: 2.1
Name: apple-reading-list-to-sqlite
Version: 0.2.2
Summary: Export Apple Reading List to SQLite
Author: ryanscott
Author-email: ryscott@gmail.com
Requires-Python: >=3.10,<4.0
Classifier: Programming Language :: Python :: 3
Classifier: Programming Language :: Python :: 3.10
Classifier: Programming Language :: Python :: 3.11
Requires-Dist: httpx (>=0.24.0,<0.25.0)
Requires-Dist: sqlite-utils (>=3.30,<4.0)
Requires-Dist: typer[all] (>=0.7.0,<0.8.0)
